kmeans_sam/__init__.py
kmeans_sam/kmeans_sam.py
kmeans_sam-0.1.8.dist-info/METADATA
kmeans_sam-0.1.8.dist-info/WHEEL
kmeans_sam-0.1.8.dist-info/top_level.txt
kmeans_sam-0.1.8.dist-info/RECORD
