Metadata-Version: 2.1
Name: kmeans-sam
Version: 0.1.8
Summary: A package for creating subclusters of KMeansSam clusters and merging them with great flexibility
Home-page: https://github.com/nishantnischaya/k-means-sam
Author: Nishant Nischaya
Author-email: nishantnischaya@gmail.com
Keywords: k-means,sub-clustering,Merging,clustering,clusters,Machine Learning,Data Science,Python3
Classifier: Development Status :: 3 - Alpha
Classifier: Programming Language :: Python :: 3
Classifier: License :: OSI Approved :: MIT License
Classifier: Operating System :: OS Independent
